download_wrapper/__init__.py
download_wrapper/base.py
download_wrapper/helper.py
download_wrapper/http_header.py
download_wrapper/wget.py
download_wrapper-0.1.dist-info/DESCRIPTION.rst
download_wrapper-0.1.dist-info/METADATA
download_wrapper-0.1.dist-info/RECORD
download_wrapper-0.1.dist-info/WHEEL
download_wrapper-0.1.dist-info/metadata.json
download_wrapper-0.1.dist-info/top_level.txt
